s_translation/__init__.py
s_translation/gettext.py
s_translation/message_creator.py
s_translation/settings.py
s_translation/utils/__init__.py
s_translation/utils/print_color.py
s_translation-1.0.0.dist-info/METADATA
s_translation-1.0.0.dist-info/WHEEL
s_translation-1.0.0.dist-info/licenses/LICENSE
s_translation-1.0.0.dist-info/RECORD
