Metadata-Version: 2.1
Name: s-translation
Version: 1.0.0
Summary: A package for easy creating and using translated messages withgettext in python projects
Project-URL: Homepage, https://github.com/ptbang/S-Translate
Project-URL: Bug Tracker, https://github.com/ptbang/S-Translate/issues
Author-email: Bang Phan <ptbang@gmail.com>
License-File: LICENSE
Classifier: License :: OSI Approved :: MIT License
Classifier: Operating System :: OS Independent
Classifier: Programming Language :: Python :: 3
Classifier: Programming Language :: Python :: 3.10
Classifier: Programming Language :: Python :: 3.11
Requires-Python: >=3.10
Requires-Dist: python-dotenv
